dask-stubs/__init__.pyi
dask-stubs/dask/__init__.pyi
dask-stubs/dask/array/__init__.pyi
dask-stubs/dask/bag/__init__.pyi
dask-stubs/dask/dataframe/__init__.pyi
dask-stubs/dask/delayed.pyi
dask-stubs/dask/distributed/__init__.pyi
dask-stubs/distributed/__init__.pyi
dask_stubs-0.1.3.dist-info/WHEEL
dask_stubs-0.1.3.dist-info/METADATA
dask_stubs-0.1.3.dist-info/RECORD
