Metadata-Version: 2.3
Name: dask-stubs
Version: 0.1.3
Summary: Typing stubs for the Dask ecosystem.
Keywords: typing,type-stubs,dask
Author: Clouder0
Author-email: Clouder0 <clouder0@outlook.com>
Classifier: Development Status :: 2 - Pre-Alpha
Classifier: Intended Audience :: Developers
Classifier: License :: OSI Approved :: MIT License
Classifier: Programming Language :: Python :: 3
Classifier: Programming Language :: Python :: 3.12
Classifier: Programming Language :: Python :: 3.13
Classifier: Typing :: Typed
Requires-Python: >=3.12
